<Properties StartupConfiguration="{B403EE69-27A7-4F8D-B501-585A98D61785}|Default">
  <MonoDevelop.Ide.ItemProperties.Ejercicio.iOS FirstBuild="True" />
  <MonoDevelop.Ide.Workbench ActiveDocument="Ejercicio/MainPage.xaml">
    <Files>
      <File FileName="Ejercicio/MainPage.xaml.cs" Line="24" Column="46" />
      <File FileName="Ejercicio/MainPage.xaml" Line="29" Column="15" />
      <File FileName="Ejercicio/viewmodel/AddCarViewModel.cs" Line="42" Column="33" />
      <File FileName="Ejercicio/models/Car.cs" Line="14" Column="6" />
    </Files>
    <Pads>
      <Pad Id="ProjectPad">
        <State name="__root__">
          <Node name="Ejercicio" expanded="True" selected="True">
            <Node name="Ejercicio" expanded="True">
              <Node name="models" expanded="True" />
              <Node name="viewmodel" expanded="True" />
              <Node name="MainPage.xaml" expanded="True" />
            </Node>
          </Node>
        </State>
      </Pad>
    </Pads>
  </MonoDevelop.Ide.Workbench>
  <MonoDevelop.Ide.ItemProperties.Ejercicio.Android AndroidDesignerPreferredTheme="Theme.AppCompat.Light.NoActionBar" PreferredExecutionTarget="Android.Android_Accelerated_Oreo" />
  <MonoDevelop.Ide.DebuggingService.PinnedWatches />
  <MonoDevelop.Ide.Workspace ActiveConfiguration="Debug" />
  <MonoDevelop.Ide.DebuggingService.Breakpoints>
    <BreakpointStore />
  </MonoDevelop.Ide.DebuggingService.Breakpoints>
  <MultiItemStartupConfigurations />
</Properties>